DESCRIPTION.md
MANIFEST.in
README.md
REQUIREMENTS
setup.py
version.conf
src/m3_ssosp.egg-info/PKG-INFO
src/m3_ssosp.egg-info/SOURCES.txt
src/m3_ssosp.egg-info/dependency_links.txt
src/m3_ssosp.egg-info/requires.txt
src/m3_ssosp.egg-info/top_level.txt
src/ssosp/__init__.py
src/ssosp/assertion_parser.py
src/ssosp/exceptions.py
src/ssosp/models.py
src/ssosp/request_response.py
src/ssosp/settings.py
src/ssosp/urls.py
src/ssosp/utils.py
src/ssosp/views.py
src/ssosp/backends/__init__.py
src/ssosp/backends/base.py
src/ssosp/backends/cache.py
src/ssosp/backends/db.py
src/ssosp/migrations/0001_initial.py
src/ssosp/migrations/__init__.py
src/ssosp/south_migrations/0001_initial.py
src/ssosp/south_migrations/__init__.py